namelov/__init__.py
namelov/hello.py
namelov-0.2.0.dist-info/WHEEL
namelov-0.2.0.dist-info/entry_points.txt
namelov-0.2.0.dist-info/METADATA
namelov-0.2.0.dist-info/RECORD
