Metadata-Version: 2.3
Name: namelov
Version: 0.2.0
Summary: A lovely package that's describes your name in a lovely way
Author: GVKarthik-dev
Author-email: GVKarthik-dev <gokaraju3705@gmail.com>
Requires-Python: >=3.5
